sitecustomize.py
pydantic_pylint-0.22.1.dist-info/METADATA
pydantic_pylint-0.22.1.dist-info/WHEEL
pydantic_pylint-0.22.1.dist-info/top_level.txt
pydantic_pylint-0.22.1.dist-info/RECORD
