Metadata-Version: 2.4
Name: pydantic-pylint
Version: 0.22.1
Summary: A Pylint plugin to help Pylint understand Pydantic
Author: John W
Classifier: Programming Language :: Python :: 3
Classifier: License :: OSI Approved :: MIT License
Dynamic: author
Dynamic: classifier
Dynamic: summary
